token_middleware/__init__.py
token_middleware/client.py
token_middleware/enums.py
token_middleware/middleware.py
token_middleware-1.0.6.dist-info/LICENSE
token_middleware-1.0.6.dist-info/METADATA
token_middleware-1.0.6.dist-info/WHEEL
token_middleware-1.0.6.dist-info/RECORD
